README.md
greek_stemmer_plus/__init__.py
greek_stemmer_plus/stemmer.yml
greek_stemmer_plus-0.2.0.dist-info/METADATA
greek_stemmer_plus-0.2.0.dist-info/WHEEL
greek_stemmer_plus-0.2.0.dist-info/RECORD
