Metadata-Version: 2.1
Name: greek-stemmer-plus
Version: 0.2.0
Summary: Python Greek stemmer.
Home-page: https://github.com/germanattanasio/python_greek_stemmer
License: MIT
Keywords: stemmer,greek,nlp
Author: German Attanasio
Author-email: germanattanasio@gmail.com
Requires-Python: >3.8
Classifier: Development Status :: 5 - Production/Stable
Classifier: Intended Audience :: Developers
Classifier: License :: OSI Approved :: MIT License
Classifier: Programming Language :: Python
Classifier: Programming Language :: Python :: 3
Classifier: Programming Language :: Python :: 3.9
Classifier: Programming Language :: Python :: 3.10
Classifier: Programming Language :: Python :: 3.11
Requires-Dist: PyYAML (>5.1.0)
